traycer/__init__.py
traycer/traycer.py
traycer-0.1.dist-info/LICENSE
traycer-0.1.dist-info/METADATA
traycer-0.1.dist-info/WHEEL
traycer-0.1.dist-info/top_level.txt
traycer-0.1.dist-info/RECORD
