Metadata-Version: 2.1
Name: traycer
Version: 0.1
Summary: a python ray tracer
Home-page: https://github.com/bpops/traycer
Author: bpops
License: MIT
License-File: LICENSE
Requires-Dist: numpy
Requires-Dist: tqdm
